{"original": {"daily_pnl": [{"date": "2025-12-01", "pnl": 0}, {"date": "2025-12-02", "pnl": 0}, {"date": "2025-12-03", "pnl": -103.72}, {"date": "2025-12-04", "pnl": -257.87}, {"date": "2025-12-05", "pnl": 0}, {"date": "2025-12-08", "pnl": 0}, {"date": "2025-12-09", "pnl": -332.98}, {"date": "2025-12-10", "pnl": 0}, {"date": "2025-12-11", "pnl": 0}, {"date": "2025-12-12", "pnl": 0}, {"date": "2025-12-15", "pnl": 0}, {"date": "2025-12-16", "pnl": 0}, {"date": "2025-12-17", "pnl": -182.02}, {"date": "2025-12-18", "pnl": -163.02}, {"date": "2025-12-19", "pnl": 64.03}, {"date": "2025-12-23", "pnl": 0}, {"date": "2025-12-24", "pnl": 46.03}, {"date": "2025-12-26", "pnl": 113.11}, {"date": "2025-12-29", "pnl": 0}, {"date": "2025-12-30", "pnl": 0}, {"date": "2025-12-31", "pnl": 0}, {"date": "2026-01-01", "pnl": 0}, {"date": "2026-01-02", "pnl": 0}, {"date": "2026-01-05", "pnl": -454.9}, {"date": "2026-01-06", "pnl": -454.29}, {"date": "2026-01-07", "pnl": -39.1}, {"date": "2026-01-08", "pnl": 0}, {"date": "2026-01-09", "pnl": 0}, {"date": "2026-01-12", "pnl": -457.01}, {"date": "2026-01-13", "pnl": 1710.88}, {"date": "2026-01-14", "pnl": -627.44}, {"date": "2026-01-16", "pnl": 1322.94}, {"date": "2026-01-19", "pnl": 270.22}, {"date": "2026-01-20", "pnl": 3698.8}, {"date": "2026-01-21", "pnl": -2127.72}, {"date": "2026-01-22", "pnl": -1967.36}, {"date": "2026-01-23", "pnl": 0}, {"date": "2026-01-27", "pnl": -1416.93}, {"date": "2026-01-28", "pnl": -1185.51}, {"date": "2026-01-29", "pnl": 0}, {"date": "2026-01-30", "pnl": -970.88}, {"date": "2026-02-01", "pnl": -269.15}, {"date": "2026-02-02", "pnl": -2035.11}, {"date": "2026-02-03", "pnl": -2484.73}, {"date": "2026-02-04", "pnl": 302.03}, {"date": "2026-02-05", "pnl": -1804.14}, {"date": "2026-02-06", "pnl": 0}, {"date": "2026-02-09", "pnl": 0}, {"date": "2026-02-10", "pnl": -944.86}, {"date": "2026-02-11", "pnl": -841.82}, {"date": "2026-02-12", "pnl": -727.8}, {"date": "2026-02-13", "pnl": -1007.79}, {"date": "2026-02-16", "pnl": -127.05}, {"date": "2026-02-17", "pnl": -311.32}, {"date": "2026-02-18", "pnl": -1767.31}, {"date": "2026-02-19", "pnl": 3961.88}, {"date": "2026-02-20", "pnl": 0}, {"date": "2026-02-23", "pnl": -1692.89}], "equity": [{"date": "2025-12-01", "equity": 0}, {"date": "2025-12-02", "equity": 0}, {"date": "2025-12-03", "equity": -103.72}, {"date": "2025-12-04", "equity": -361.58}, {"date": "2025-12-05", "equity": -361.58}, {"date": "2025-12-08", "equity": -361.58}, {"date": "2025-12-09", "equity": -694.56}, {"date": "2025-12-10", "equity": -694.56}, {"date": "2025-12-11", "equity": -694.56}, {"date": "2025-12-12", "equity": -694.56}, {"date": "2025-12-15", "equity": -694.56}, {"date": "2025-12-16", "equity": -694.56}, {"date": "2025-12-17", "equity": -876.58}, {"date": "2025-12-18", "equity": -1039.6}, {"date": "2025-12-19", "equity": -975.57}, {"date": "2025-12-23", "equity": -975.57}, {"date": "2025-12-24", "equity": -929.54}, {"date": "2025-12-26", "equity": -816.43}, {"date": "2025-12-29", "equity": -816.43}, {"date": "2025-12-30", "equity": -816.43}, {"date": "2025-12-31", "equity": -816.43}, {"date": "2026-01-01", "equity": -816.43}, {"date": "2026-01-02", "equity": -816.43}, {"date": "2026-01-05", "equity": -1271.33}, {"date": "2026-01-06", "equity": -1725.62}, {"date": "2026-01-07", "equity": -1764.72}, {"date": "2026-01-08", "equity": -1764.72}, {"date": "2026-01-09", "equity": -1764.72}, {"date": "2026-01-12", "equity": -2221.73}, {"date": "2026-01-13", "equity": -510.85}, {"date": "2026-01-14", "equity": -1138.29}, {"date": "2026-01-16", "equity": 184.65}, {"date": "2026-01-19", "equity": 454.86}, {"date": "2026-01-20", "equity": 4153.66}, {"date": "2026-01-21", "equity": 2025.94}, {"date": "2026-01-22", "equity": 58.57}, {"date": "2026-01-23", "equity": 58.57}, {"date": "2026-01-27", "equity": -1358.36}, {"date": "2026-01-28", "equity": -2543.86}, {"date": "2026-01-29", "equity": -2543.86}, {"date": "2026-01-30", "equity": -3514.75}, {"date": "2026-02-01", "equity": -3783.89}, {"date": "2026-02-02", "equity": -5819.0}, {"date": "2026-02-03", "equity": -8303.73}, {"date": "2026-02-04", "equity": -8001.7}, {"date": "2026-02-05", "equity": -9805.84}, {"date": "2026-02-06", "equity": -9805.84}, {"date": "2026-02-09", "equity": -9805.84}, {"date": "2026-02-10", "equity": -10750.7}, {"date": "2026-02-11", "equity": -11592.52}, {"date": "2026-02-12", "equity": -12320.32}, {"date": "2026-02-13", "equity": -13328.11}, {"date": "2026-02-16", "equity": -13455.16}, {"date": "2026-02-17", "equity": -13766.47}, {"date": "2026-02-18", "equity": -15533.79}, {"date": "2026-02-19", "equity": -11571.91}, {"date": "2026-02-20", "equity": -11571.91}, {"date": "2026-02-23", "equity": -13264.8}], "trades": [{"date": "2025-12-03", "entry_time": "09:46", "exit_time": "15:15", "side": "PUT", "symbol": "NIFTY26200PE", "entry": 444.0, "exit": 442.5, "gross": -37.5, "net": -103.72, "reason": "FORCE_EXIT"}, {"date": "2025-12-04", "entry_time": "10:16", "exit_time": "14:58", "side": "CALL", "symbol": "NIFTY25800CE", "entry": 952.0, "exit": 945.2, "gross": -170.0, "net": -257.87, "reason": "PREMIUM_TRAIL_SL"}, {"date": "2025-12-09", "entry_time": "10:01", "exit_time": "10:19", "side": "PUT", "symbol": "NIFTY26050PE", "entry": 452.05, "exit": 448.05, "gross": -100.0, "net": -166.49, "reason": "CANDLE_SL"}, {"date": "2025-12-09", "entry_time": "10:34", "exit_time": "11:09", "side": "PUT", "symbol": "NIFTY26050PE", "entry": 452.05, "exit": 448.05, "gross": -100.0, "net": -166.49, "reason": "CANDLE_SL"}, {"date": "2025-12-17", "entry_time": "09:29", "exit_time": "09:44", "side": "CALL", "symbol": "NIFTY25700CE", "entry": 813.8, "exit": 809.8, "gross": -100.0, "net": -182.02, "reason": "CANDLE_SL"}, {"date": "2025-12-18", "entry_time": "09:52", "exit_time": "10:11", "side": "PUT", "symbol": "NIFTY25950PE", "entry": 371.3, "exit": 367.3, "gross": -100.0, "net": -163.02, "reason": "CANDLE_SL"}, {"date": "2025-12-19", "entry_time": "09:44", "exit_time": "15:15", "side": "CALL", "symbol": "NIFTY25700CE", "entry": 841.1, "exit": 847.0, "gross": 147.5, "net": 64.03, "reason": "FORCE_EXIT"}, {"date": "2025-12-24", "entry_time": "09:34", "exit_time": "11:43", "side": "CALL", "symbol": "NIFTY25950CE", "entry": 824.0, "exit": 829.15, "gross": 128.75, "net": 46.03, "reason": "CANDLE_SL"}, {"date": "2025-12-26", "entry_time": "09:58", "exit_time": "15:15", "side": "PUT", "symbol": "NIFTY26300PE", "entry": 366.6, "exit": 373.65, "gross": 176.25, "net": 113.11, "reason": "FORCE_EXIT"}, {"date": "2026-01-05", "entry_time": "09:25", "exit_time": "10:10", "side": "PUT", "symbol": "NIFTY26550PE", "entry": 393.7, "exit": 378.05, "gross": -391.25, "net": -454.9, "reason": "CANDLE_SL"}, {"date": "2026-01-06", "entry_time": "09:57", "exit_time": "10:21", "side": "CALL", "symbol": "NIFTY26000CE", "entry": 728.5, "exit": 713.45, "gross": -376.25, "net": -454.29, "reason": "CANDLE_SL"}, {"date": "2026-01-07", "entry_time": "09:53", "exit_time": "09:56", "side": "PUT", "symbol": "NIFTY26350PE", "entry": 393.0, "exit": 394.0, "gross": 25.0, "net": -39.1, "reason": "CANDLE_SL"}, {"date": "2026-01-12", "entry_time": "09:35", "exit_time": "12:17", "side": "PUT", "symbol": "NIFTY25850PE", "entry": 413.9, "exit": 398.2, "gross": -392.5, "net": -457.01, "reason": "PREMIUM_TRAIL_SL"}, {"date": "2026-01-13", "entry_time": "09:21", "exit_time": "10:23", "side": "PUT", "symbol": "NIFTY26100PE", "entry": 428.0, "exit": 450.8, "gross": 570.0, "net": 503.77, "reason": "PREMIUM_TRAIL_SL"}, {"date": "2026-01-13", "entry_time": "10:35", "exit_time": "14:37", "side": "PUT", "symbol": "NIFTY26100PE", "entry": 447.75, "exit": 498.75, "gross": 1275.0, "net": 1207.11, "reason": "PREMIUM_TRAIL_SL"}, {"date": "2026-01-14", "entry_time": "09:23", "exit_time": "09:44", "side": "CALL", "symbol": "NIFTY25450CE", "entry": 680.0, "exit": 678.0, "gross": -50.0, "net": -126.33, "reason": "CANDLE_SL"}, {"date": "2026-01-14", "entry_time": "09:54", "exit_time": "10:08", "side": "CALL", "symbol": "NIFTY25450CE", "entry": 642.5, "exit": 638.5, "gross": -100.0, "net": -174.66, "reason": "CANDLE_SL"}, {"date": "2026-01-14", "entry_time": "11:20", "exit_time": "13:32", "side": "CALL", "symbol": "NIFTY25450CE", "entry": 688.0, "exit": 678.0, "gross": -250.0, "net": -326.44, "reason": "CANDLE_SL"}, {"date": "2026-01-16", "entry_time": "09:57", "exit_time": "11:12", "side": "CALL", "symbol": "NIFTY25500CE", "entry": 658.0, "exit": 714.0, "gross": 1400.0, "net": 1322.94, "reason": "PREMIUM_TRAIL_SL"}, {"date": "2026-01-19", "entry_time": "10:08", "exit_time": "11:00", "side": "PUT", "symbol": "NIFTY25850PE", "entry": 447.0, "exit": 447.65, "gross": 16.25, "net": -50.16, "reason": "CANDLE_SL"}, {"date": "2026-01-19", "entry_time": "11:21", "exit_time": "12:17", "side": "PUT", "symbol": "NIFTY25850PE", "entry": 424.7, "exit": 440.15, "gross": 386.25, "net": 320.37, "reason": "CANDLE_SL"}, {"date": "2026-01-20", "entry_time": "09:51", "exit_time": "15:10", "side": "PUT", "symbol": "NIFTY25800PE", "entry": 457.7, "exit": 608.5, "gross": 3770.0, "net": 3698.8, "reason": "PREMIUM_TARGET"}, {"date": "2026-01-21", "entry_time": "09:19", "exit_time": "10:21", "side": "CALL", "symbol": "NIFTY24950CE", "entry": 708.05, "exit": 625.95, "gross": -2052.5, "net": -2127.72, "reason": "CANDLE_SL"}, {"date": "2026-01-22", "entry_time": "09:52", "exit_time": "10:20", "side": "CALL", "symbol": "NIFTY25150CE", "entry": 666.35, "exit": 590.6, "gross": -1893.75, "net": -1967.36, "reason": "CANDLE_SL"}, {"date": "2026-01-27", "entry_time": "09:27", "exit_time": "09:37", "side": "PUT", "symbol": "NIFTY25250PE", "entry": 496.0, "exit": 442.0, "gross": -1350.0, "net": -1416.93, "reason": "CANDLE_SL"}, {"date": "2026-01-28", "entry_time": "09:32", "exit_time": "09:38", "side": "CALL", "symbol": "NIFTY25050CE", "entry": 657.75, "exit": 619.35, "gross": -960.0, "net": -1034.32, "reason": "CANDLE_SL"}, {"date": "2026-01-28", "entry_time": "11:25", "exit_time": "11:42", "side": "CALL", "symbol": "NIFTY25050CE", "entry": 619.0, "exit": 615.9, "gross": -77.5, "net": -151.18, "reason": "CANDLE_SL"}, {"date": "2026-01-30", "entry_time": "09:38", "exit_time": "11:10", "side": "CALL", "symbol": "NIFTY25050CE", "entry": 576.0, "exit": 540.0, "gross": -900.0, "net": -970.88, "reason": "CANDLE_SL"}, {"date": "2026-02-01", "entry_time": "10:17", "exit_time": "11:41", "side": "CALL", "symbol": "NIFTY25150CE", "entry": 516.7, "exit": 508.7, "gross": -200.0, "net": -269.15, "reason": "PREMIUM_TRAIL_SL"}, {"date": "2026-02-02", "entry_time": "09:21", "exit_time": "10:00", "side": "CALL", "symbol": "NIFTY24600CE", "entry": 549.45, "exit": 542.3, "gross": -178.75, "net": -249.33, "reason": "PREMIUM_TRAIL_SL"}, {"date": "2026-02-02", "entry_time": "10:40", "exit_time": "10:57", "side": "CALL", "symbol": "NIFTY24600CE", "entry": 566.35, "exit": 497.7, "gross": -1716.25, "net": -1785.78, "reason": "CANDLE_SL"}, {"date": "2026-02-03", "entry_time": "09:59", "exit_time": "10:26", "side": "PUT", "symbol": "NIFTY26500PE", "entry": 816.75, "exit": 730.5, "gross": -2156.25, "net": -2236.02, "reason": "CANDLE_SL"}, {"date": "2026-02-03", "entry_time": "10:54", "exit_time": "10:55", "side": "PUT", "symbol": "NIFTY26500PE", "entry": 738.7, "exit": 731.9, "gross": -170.0, "net": -248.71, "reason": "CANDLE_SL"}, {"date": "2026-02-04", "entry_time": "09:23", "exit_time": "10:23", "side": "CALL", "symbol": "NIFTY25500CE", "entry": 475.5, "exit": 470.5, "gross": -125.0, "net": -192.47, "reason": "PREMIUM_TRAIL_SL"}, {"date": "2026-02-04", "entry_time": "10:43", "exit_time": "15:08", "side": "CALL", "symbol": "NIFTY25500CE", "entry": 469.5, "exit": 492.0, "gross": 562.5, "net": 494.5, "reason": "PREMIUM_TRAIL_SL"}, {"date": "2026-02-05", "entry_time": "09:58", "exit_time": "10:22", "side": "PUT", "symbol": "NIFTY25950PE", "entry": 408.9, "exit": 357.9, "gross": -1275.0, "net": -1338.28, "reason": "CANDLE_SL"}, {"date": "2026-02-05", "entry_time": "10:31", "exit_time": "11:14", "side": "PUT", "symbol": "NIFTY25950PE", "entry": 365.15, "exit": 359.0, "gross": -153.75, "net": -216.45, "reason": "PREMIUM_TRAIL_SL"}, {"date": "2026-02-05", "entry_time": "11:19", "exit_time": "15:03", "side": "PUT", "symbol": "NIFTY25950PE", "entry": 377.0, "exit": 369.55, "gross": -186.25, "net": -249.42, "reason": "PREMIUM_TRAIL_SL"}, {"date": "2026-02-10", "entry_time": "09:49", "exit_time": "13:32", "side": "CALL", "symbol": "NIFTY25700CE", "entry": 406.0, "exit": 370.75, "gross": -881.25, "net": -944.86, "reason": "CANDLE_SL"}, {"date": "2026-02-11", "entry_time": "09:44", "exit_time": "09:55", "side": "PUT", "symbol": "NIFTY26200PE", "entry": 295.1, "exit": 284.0, "gross": -277.5, "net": -337.05, "reason": "CANDLE_SL"}, {"date": "2026-02-11", "entry_time": "10:08", "exit_time": "10:19", "side": "PUT", "symbol": "NIFTY26200PE", "entry": 304.95, "exit": 287.15, "gross": -445.0, "net": -504.78, "reason": "CANDLE_SL"}, {"date": "2026-02-12", "entry_time": "09:40", "exit_time": "09:49", "side": "PUT", "symbol": "NIFTY26100PE", "entry": 294.7, "exit": 284.3, "gross": -260.0, "net": -319.55, "reason": "CANDLE_SL"}, {"date": "2026-02-12", "entry_time": "11:25", "exit_time": "12:57", "side": "PUT", "symbol": "NIFTY26100PE", "entry": 295.95, "exit": 282.0, "gross": -348.75, "net": -408.25, "reason": "CANDLE_SL"}, {"date": "2026-02-13", "entry_time": "10:01", "exit_time": "10:33", "side": "PUT", "symbol": "NIFTY25750PE", "entry": 254.2, "exit": 247.6, "gross": -165.0, "net": -222.92, "reason": "CANDLE_SL"}, {"date": "2026-02-13", "entry_time": "10:50", "exit_time": "10:55", "side": "PUT", "symbol": "NIFTY25750PE", "entry": 259.8, "exit": 246.45, "gross": -333.75, "net": -391.72, "reason": "CANDLE_SL"}, {"date": "2026-02-13", "entry_time": "11:04", "exit_time": "12:02", "side": "PUT", "symbol": "NIFTY25750PE", "entry": 264.1, "exit": 250.7, "gross": -335.0, "net": -393.15, "reason": "CANDLE_SL"}, {"date": "2026-02-16", "entry_time": "09:20", "exit_time": "09:51", "side": "CALL", "symbol": "NIFTY25200CE", "entry": 395.0, "exit": 370.15, "gross": -621.25, "net": -684.69, "reason": "CANDLE_SL"}, {"date": "2026-02-16", "entry_time": "09:55", "exit_time": "11:46", "side": "CALL", "symbol": "NIFTY25200CE", "entry": 394.7, "exit": 419.6, "gross": 622.5, "net": 557.64, "reason": "PREMIUM_TRAIL_SL"}, {"date": "2026-02-17", "entry_time": "09:32", "exit_time": "09:33", "side": "PUT", "symbol": "NIFTY25850PE", "entry": 306.55, "exit": 296.5, "gross": -251.25, "net": -311.32, "reason": "CANDLE_SL"}, {"date": "2026-02-18", "entry_time": "09:25", "exit_time": "09:27", "side": "PUT", "symbol": "NIFTY25950PE", "entry": 269.2, "exit": 256.25, "gross": -323.75, "net": -382.13, "reason": "CANDLE_SL"}, {"date": "2026-02-18", "entry_time": "10:11", "exit_time": "12:35", "side": "PUT", "symbol": "NIFTY25950PE", "entry": 309.05, "exit": 256.0, "gross": -1326.25, "net": -1385.18, "reason": "CANDLE_SL"}, {"date": "2026-02-19", "entry_time": "09:29", "exit_time": "12:01", "side": "PUT", "symbol": "NIFTY26050PE", "entry": 262.5, "exit": 423.5, "gross": 4025.0, "net": 3961.88, "reason": "PREMIUM_TARGET"}, {"date": "2026-02-23", "entry_time": "09:38", "exit_time": "10:38", "side": "CALL", "symbol": "NIFTY25500CE", "entry": 293.05, "exit": 227.65, "gross": -1635.0, "net": -1692.89, "reason": "CANDLE_SL"}], "exit_reasons": {"FORCE_EXIT": 3, "PREMIUM_TRAIL_SL": 12, "CANDLE_SL": 36, "PREMIUM_TARGET": 2}, "metrics": {"total_trades": 53, "winning_trades": 11, "win_rate": 20.8, "gross_pnl": -9661.0, "net_pnl": -13265.0, "charges": 3604.0, "avg_win": 1117.0, "avg_loss": -608.0, "rr": 1.84, "pf": 0.48, "max_dd": 19687.0, "sharpe": -3.32}}, "tuned": {"daily_pnl": [{"date": "2025-12-01", "pnl": 0}, {"date": "2025-12-02", "pnl": 0}, {"date": "2025-12-03", "pnl": 221.47}, {"date": "2025-12-04", "pnl": -257.87}, {"date": "2025-12-05", "pnl": 0}, {"date": "2025-12-08", "pnl": 0}, {"date": "2025-12-09", "pnl": 854.08}, {"date": "2025-12-10", "pnl": 0}, {"date": "2025-12-11", "pnl": 0}, {"date": "2025-12-12", "pnl": 0}, {"date": "2025-12-15", "pnl": 0}, {"date": "2025-12-16", "pnl": 0}, {"date": "2025-12-17", "pnl": -182.02}, {"date": "2025-12-18", "pnl": -163.02}, {"date": "2025-12-19", "pnl": 466.75}, {"date": "2025-12-23", "pnl": 0}, {"date": "2025-12-24", "pnl": 46.03}, {"date": "2025-12-26", "pnl": 278.2}, {"date": "2025-12-29", "pnl": 0}, {"date": "2025-12-30", "pnl": 0}, {"date": "2025-12-31", "pnl": 0}, {"date": "2026-01-01", "pnl": 0}, {"date": "2026-01-02", "pnl": 0}, {"date": "2026-01-05", "pnl": -454.9}, {"date": "2026-01-06", "pnl": -541.84}, {"date": "2026-01-07", "pnl": -39.1}, {"date": "2026-01-08", "pnl": 0}, {"date": "2026-01-09", "pnl": 0}, {"date": "2026-01-12", "pnl": -350.7}, {"date": "2026-01-13", "pnl": 514.76}, {"date": "2026-01-14", "pnl": -300.99}, {"date": "2026-01-16", "pnl": 552.75}, {"date": "2026-01-19", "pnl": 170.16}, {"date": "2026-01-20", "pnl": 4968.79}, {"date": "2026-01-21", "pnl": -2127.72}, {"date": "2026-01-22", "pnl": -530.31}, {"date": "2026-01-23", "pnl": 0}, {"date": "2026-01-27", "pnl": -1516.99}, {"date": "2026-01-28", "pnl": -1141.73}, {"date": "2026-01-29", "pnl": 0}, {"date": "2026-01-30", "pnl": -970.88}, {"date": "2026-02-01", "pnl": -417.48}, {"date": "2026-02-02", "pnl": -2035.11}, {"date": "2026-02-03", "pnl": -1491.71}, {"date": "2026-02-04", "pnl": 399.35}, {"date": "2026-02-05", "pnl": -646.07}, {"date": "2026-02-06", "pnl": 0}, {"date": "2026-02-09", "pnl": 0}, {"date": "2026-02-10", "pnl": -877.32}, {"date": "2026-02-11", "pnl": -934.37}, {"date": "2026-02-12", "pnl": -721.57}, {"date": "2026-02-13", "pnl": -593.37}, {"date": "2026-02-16", "pnl": 3452.56}, {"date": "2026-02-17", "pnl": -578.97}, {"date": "2026-02-18", "pnl": -581.37}, {"date": "2026-02-19", "pnl": 5019.39}, {"date": "2026-02-20", "pnl": 0}, {"date": "2026-02-23", "pnl": -251.75}], "equity": [{"date": "2025-12-01", "equity": 0}, {"date": "2025-12-02", "equity": 0}, {"date": "2025-12-03", "equity": 221.47}, {"date": "2025-12-04", "equity": -36.4}, {"date": "2025-12-05", "equity": -36.4}, {"date": "2025-12-08", "equity": -36.4}, {"date": "2025-12-09", "equity": 817.68}, {"date": "2025-12-10", "equity": 817.68}, {"date": "2025-12-11", "equity": 817.68}, {"date": "2025-12-12", "equity": 817.68}, {"date": "2025-12-15", "equity": 817.68}, {"date": "2025-12-16", "equity": 817.68}, {"date": "2025-12-17", "equity": 635.67}, {"date": "2025-12-18", "equity": 472.64}, {"date": "2025-12-19", "equity": 939.39}, {"date": "2025-12-23", "equity": 939.39}, {"date": "2025-12-24", "equity": 985.43}, {"date": "2025-12-26", "equity": 1263.63}, {"date": "2025-12-29", "equity": 1263.63}, {"date": "2025-12-30", "equity": 1263.63}, {"date": "2025-12-31", "equity": 1263.63}, {"date": "2026-01-01", "equity": 1263.63}, {"date": "2026-01-02", "equity": 1263.63}, {"date": "2026-01-05", "equity": 808.73}, {"date": "2026-01-06", "equity": 266.9}, {"date": "2026-01-07", "equity": 227.8}, {"date": "2026-01-08", "equity": 227.8}, {"date": "2026-01-09", "equity": 227.8}, {"date": "2026-01-12", "equity": -122.91}, {"date": "2026-01-13", "equity": 391.85}, {"date": "2026-01-14", "equity": 90.86}, {"date": "2026-01-16", "equity": 643.61}, {"date": "2026-01-19", "equity": 813.77}, {"date": "2026-01-20", "equity": 5782.56}, {"date": "2026-01-21", "equity": 3654.84}, {"date": "2026-01-22", "equity": 3124.53}, {"date": "2026-01-23", "equity": 3124.53}, {"date": "2026-01-27", "equity": 1607.54}, {"date": "2026-01-28", "equity": 465.81}, {"date": "2026-01-29", "equity": 465.81}, {"date": "2026-01-30", "equity": -505.07}, {"date": "2026-02-01", "equity": -922.55}, {"date": "2026-02-02", "equity": -2957.66}, {"date": "2026-02-03", "equity": -4449.37}, {"date": "2026-02-04", "equity": -4050.02}, {"date": "2026-02-05", "equity": -4696.09}, {"date": "2026-02-06", "equity": -4696.09}, {"date": "2026-02-09", "equity": -4696.09}, {"date": "2026-02-10", "equity": -5573.41}, {"date": "2026-02-11", "equity": -6507.78}, {"date": "2026-02-12", "equity": -7229.35}, {"date": "2026-02-13", "equity": -7822.73}, {"date": "2026-02-16", "equity": -4370.17}, {"date": "2026-02-17", "equity": -4949.14}, {"date": "2026-02-18", "equity": -5530.51}, {"date": "2026-02-19", "equity": -511.12}, {"date": "2026-02-20", "equity": -511.12}, {"date": "2026-02-23", "equity": -762.87}], "trades": [{"date": "2025-12-03", "entry_time": "09:27", "exit_time": "15:15", "side": "PUT", "symbol": "NIFTY26200PE", "entry": 431.0, "exit": 442.5, "gross": 287.5, "net": 221.47, "reason": "FORCE_EXIT"}, {"date": "2025-12-04", "entry_time": "10:16", "exit_time": "15:15", "side": "CALL", "symbol": "NIFTY25800CE", "entry": 952.0, "exit": 945.2, "gross": -170.0, "net": -257.87, "reason": "FORCE_EXIT"}, {"date": "2025-12-09", "entry_time": "09:26", "exit_time": "15:15", "side": "PUT", "symbol": "NIFTY26050PE", "entry": 411.25, "exit": 448.05, "gross": 920.0, "net": 854.08, "reason": "FORCE_EXIT"}, {"date": "2025-12-17", "entry_time": "09:23", "exit_time": "09:44", "side": "CALL", "symbol": "NIFTY25700CE", "entry": 813.8, "exit": 809.8, "gross": -100.0, "net": -182.02, "reason": "CANDLE_SL"}, {"date": "2025-12-18", "entry_time": "09:43", "exit_time": "10:11", "side": "PUT", "symbol": "NIFTY25950PE", "entry": 371.3, "exit": 367.3, "gross": -100.0, "net": -163.02, "reason": "CANDLE_SL"}, {"date": "2025-12-19", "entry_time": "09:26", "exit_time": "15:15", "side": "CALL", "symbol": "NIFTY25700CE", "entry": 825.0, "exit": 847.0, "gross": 550.0, "net": 466.75, "reason": "FORCE_EXIT"}, {"date": "2025-12-24", "entry_time": "09:33", "exit_time": "11:43", "side": "CALL", "symbol": "NIFTY25950CE", "entry": 824.0, "exit": 829.15, "gross": 128.75, "net": 46.03, "reason": "CANDLE_SL"}, {"date": "2025-12-26", "entry_time": "09:40", "exit_time": "15:15", "side": "PUT", "symbol": "NIFTY26300PE", "entry": 360.0, "exit": 373.65, "gross": 341.25, "net": 278.2, "reason": "FORCE_EXIT"}, {"date": "2026-01-05", "entry_time": "09:24", "exit_time": "10:10", "side": "PUT", "symbol": "NIFTY26550PE", "entry": 393.7, "exit": 378.05, "gross": -391.25, "net": -454.9, "reason": "CANDLE_SL"}, {"date": "2026-01-06", "entry_time": "09:56", "exit_time": "10:21", "side": "CALL", "symbol": "NIFTY26000CE", "entry": 732.0, "exit": 713.45, "gross": -463.75, "net": -541.84, "reason": "CANDLE_SL"}, {"date": "2026-01-07", "entry_time": "09:53", "exit_time": "09:56", "side": "PUT", "symbol": "NIFTY26350PE", "entry": 393.0, "exit": 394.0, "gross": 25.0, "net": -39.1, "reason": "CANDLE_SL"}, {"date": "2026-01-12", "entry_time": "09:20", "exit_time": "12:17", "side": "PUT", "symbol": "NIFTY25850PE", "entry": 409.65, "exit": 398.2, "gross": -286.25, "net": -350.7, "reason": "PREMIUM_TRAIL_SL"}, {"date": "2026-01-13", "entry_time": "09:21", "exit_time": "10:33", "side": "PUT", "symbol": "NIFTY26100PE", "entry": 428.0, "exit": 422.0, "gross": -150.0, "net": -215.4, "reason": "PREMIUM_TRAIL_SL"}, {"date": "2026-01-13", "entry_time": "10:35", "exit_time": "14:47", "side": "PUT", "symbol": "NIFTY26100PE", "entry": 447.75, "exit": 479.65, "gross": 797.5, "net": 730.16, "reason": "PREMIUM_TRAIL_SL"}, {"date": "2026-01-14", "entry_time": "09:23", "exit_time": "09:44", "side": "CALL", "symbol": "NIFTY25450CE", "entry": 680.0, "exit": 678.0, "gross": -50.0, "net": -126.33, "reason": "CANDLE_SL"}, {"date": "2026-01-14", "entry_time": "09:54", "exit_time": "10:08", "side": "CALL", "symbol": "NIFTY25450CE", "entry": 642.5, "exit": 638.5, "gross": -100.0, "net": -174.66, "reason": "CANDLE_SL"}, {"date": "2026-01-16", "entry_time": "09:53", "exit_time": "11:58", "side": "CALL", "symbol": "NIFTY25500CE", "entry": 653.95, "exit": 679.1, "gross": 628.75, "net": 552.75, "reason": "PREMIUM_TRAIL_SL"}, {"date": "2026-01-19", "entry_time": "10:01", "exit_time": "11:00", "side": "PUT", "symbol": "NIFTY25850PE", "entry": 451.0, "exit": 447.65, "gross": -83.75, "net": -150.21, "reason": "CANDLE_SL"}, {"date": "2026-01-19", "entry_time": "11:20", "exit_time": "12:17", "side": "PUT", "symbol": "NIFTY25850PE", "entry": 424.7, "exit": 440.15, "gross": 386.25, "net": 320.37, "reason": "CANDLE_SL"}, {"date": "2026-01-20", "entry_time": "09:23", "exit_time": "15:11", "side": "PUT", "symbol": "NIFTY25800PE", "entry": 423.7, "exit": 625.3, "gross": 5040.0, "net": 4968.79, "reason": "PREMIUM_TARGET"}, {"date": "2026-01-21", "entry_time": "09:19", "exit_time": "10:21", "side": "CALL", "symbol": "NIFTY24950CE", "entry": 708.05, "exit": 625.95, "gross": -2052.5, "net": -2127.72, "reason": "CANDLE_SL"}, {"date": "2026-01-22", "entry_time": "09:27", "exit_time": "10:20", "side": "CALL", "symbol": "NIFTY25150CE", "entry": 608.9, "exit": 590.6, "gross": -457.5, "net": -530.31, "reason": "PREMIUM_TRAIL_SL"}, {"date": "2026-01-27", "entry_time": "09:21", "exit_time": "09:37", "side": "PUT", "symbol": "NIFTY25250PE", "entry": 500.0, "exit": 442.0, "gross": -1450.0, "net": -1516.99, "reason": "CANDLE_SL"}, {"date": "2026-01-28", "entry_time": "09:20", "exit_time": "09:38", "side": "CALL", "symbol": "NIFTY25050CE", "entry": 656.0, "exit": 619.35, "gross": -916.25, "net": -990.55, "reason": "CANDLE_SL"}, {"date": "2026-01-28", "entry_time": "11:24", "exit_time": "11:42", "side": "CALL", "symbol": "NIFTY25050CE", "entry": 619.0, "exit": 615.9, "gross": -77.5, "net": -151.18, "reason": "CANDLE_SL"}, {"date": "2026-01-30", "entry_time": "09:38", "exit_time": "11:10", "side": "CALL", "symbol": "NIFTY25050CE", "entry": 576.0, "exit": 540.0, "gross": -900.0, "net": -970.88, "reason": "CANDLE_SL"}, {"date": "2026-02-01", "entry_time": "10:14", "exit_time": "11:42", "side": "CALL", "symbol": "NIFTY25150CE", "entry": 511.0, "exit": 497.05, "gross": -348.75, "net": -417.48, "reason": "PREMIUM_TRAIL_SL"}, {"date": "2026-02-02", "entry_time": "09:21", "exit_time": "10:00", "side": "CALL", "symbol": "NIFTY24600CE", "entry": 549.45, "exit": 542.3, "gross": -178.75, "net": -249.33, "reason": "PREMIUM_TRAIL_SL"}, {"date": "2026-02-02", "entry_time": "10:40", "exit_time": "10:57", "side": "CALL", "symbol": "NIFTY24600CE", "entry": 566.35, "exit": 497.7, "gross": -1716.25, "net": -1785.78, "reason": "CANDLE_SL"}, {"date": "2026-02-03", "entry_time": "09:35", "exit_time": "09:52", "side": "PUT", "symbol": "NIFTY26500PE", "entry": 778.65, "exit": 741.95, "gross": -917.5, "net": -997.06, "reason": "CANDLE_SL"}, {"date": "2026-02-03", "entry_time": "09:53", "exit_time": "10:18", "side": "PUT", "symbol": "NIFTY26500PE", "entry": 767.05, "exit": 750.45, "gross": -415.0, "net": -494.65, "reason": "PREMIUM_TRAIL_SL"}, {"date": "2026-02-04", "entry_time": "09:23", "exit_time": "15:15", "side": "CALL", "symbol": "NIFTY25500CE", "entry": 475.5, "exit": 494.2, "gross": 467.5, "net": 399.35, "reason": "FORCE_EXIT"}, {"date": "2026-02-05", "entry_time": "09:27", "exit_time": "09:30", "side": "PUT", "symbol": "NIFTY25950PE", "entry": 368.75, "exit": 354.0, "gross": -368.75, "net": -431.35, "reason": "CANDLE_SL"}, {"date": "2026-02-05", "entry_time": "09:38", "exit_time": "10:24", "side": "PUT", "symbol": "NIFTY25950PE", "entry": 353.95, "exit": 347.85, "gross": -152.5, "net": -214.72, "reason": "PREMIUM_TRAIL_SL"}, {"date": "2026-02-10", "entry_time": "09:34", "exit_time": "13:32", "side": "CALL", "symbol": "NIFTY25700CE", "entry": 403.3, "exit": 370.75, "gross": -813.75, "net": -877.32, "reason": "CANDLE_SL"}, {"date": "2026-02-11", "entry_time": "09:39", "exit_time": "09:55", "side": "PUT", "symbol": "NIFTY26200PE", "entry": 298.85, "exit": 284.0, "gross": -371.25, "net": -430.85, "reason": "CANDLE_SL"}, {"date": "2026-02-11", "entry_time": "10:01", "exit_time": "10:19", "side": "PUT", "symbol": "NIFTY26200PE", "entry": 304.9, "exit": 287.15, "gross": -443.75, "net": -503.52, "reason": "CANDLE_SL"}, {"date": "2026-02-12", "entry_time": "09:23", "exit_time": "09:49", "side": "PUT", "symbol": "NIFTY26100PE", "entry": 298.55, "exit": 284.3, "gross": -356.25, "net": -415.85, "reason": "CANDLE_SL"}, {"date": "2026-02-12", "entry_time": "11:07", "exit_time": "11:08", "side": "PUT", "symbol": "NIFTY26100PE", "entry": 292.45, "exit": 282.6, "gross": -246.25, "net": -305.72, "reason": "CANDLE_SL"}, {"date": "2026-02-13", "entry_time": "09:35", "exit_time": "10:33", "side": "PUT", "symbol": "NIFTY25750PE", "entry": 253.35, "exit": 247.6, "gross": -143.75, "net": -201.66, "reason": "CANDLE_SL"}, {"date": "2026-02-13", "entry_time": "10:50", "exit_time": "10:55", "side": "PUT", "symbol": "NIFTY25750PE", "entry": 259.8, "exit": 246.45, "gross": -333.75, "net": -391.72, "reason": "CANDLE_SL"}, {"date": "2026-02-16", "entry_time": "09:20", "exit_time": "09:51", "side": "CALL", "symbol": "NIFTY25200CE", "entry": 395.0, "exit": 370.15, "gross": -621.25, "net": -684.69, "reason": "CANDLE_SL"}, {"date": "2026-02-16", "entry_time": "09:55", "exit_time": "15:15", "side": "CALL", "symbol": "NIFTY25200CE", "entry": 394.7, "exit": 562.95, "gross": 4206.25, "net": 4137.25, "reason": "FORCE_EXIT"}, {"date": "2026-02-17", "entry_time": "09:21", "exit_time": "09:33", "side": "PUT", "symbol": "NIFTY25850PE", "entry": 317.25, "exit": 296.5, "gross": -518.75, "net": -578.97, "reason": "CANDLE_SL"}, {"date": "2026-02-18", "entry_time": "09:25", "exit_time": "09:27", "side": "PUT", "symbol": "NIFTY25950PE", "entry": 269.2, "exit": 256.25, "gross": -323.75, "net": -382.13, "reason": "CANDLE_SL"}, {"date": "2026-02-18", "entry_time": "09:54", "exit_time": "10:58", "side": "PUT", "symbol": "NIFTY25950PE", "entry": 284.2, "exit": 278.6, "gross": -140.0, "net": -199.24, "reason": "PREMIUM_TRAIL_SL"}, {"date": "2026-02-19", "entry_time": "09:28", "exit_time": "12:13", "side": "PUT", "symbol": "NIFTY26050PE", "entry": 262.85, "exit": 466.2, "gross": 5083.75, "net": 5019.39, "reason": "PREMIUM_TARGET"}, {"date": "2026-02-23", "entry_time": "09:21", "exit_time": "10:13", "side": "CALL", "symbol": "NIFTY25500CE", "entry": 256.9, "exit": 249.15, "gross": -193.75, "net": -251.75, "reason": "PREMIUM_TRAIL_SL"}], "exit_reasons": {"FORCE_EXIT": 7, "CANDLE_SL": 28, "PREMIUM_TRAIL_SL": 11, "PREMIUM_TARGET": 2}, "metrics": {"total_trades": 48, "winning_trades": 12, "win_rate": 25.0, "gross_pnl": 2510.0, "net_pnl": -763.0, "charges": 3273.0, "avg_win": 1500.0, "avg_loss": -521.0, "rr": 2.88, "pf": 0.96, "max_dd": 13605.0, "sharpe": -0.17}}}